xrexpr/__init__.py
xrexpr/_version.py
xrexpr/cst.py
xrexpr/decorators.py
xrexpr-0.0.1.dist-info/METADATA
xrexpr-0.0.1.dist-info/WHEEL
xrexpr-0.0.1.dist-info/top_level.txt
xrexpr-0.0.1.dist-info/RECORD
