Metadata-Version: 2.4
Name: xrexpr
Version: 0.0.1
Summary: Rewrite chained expressions on xarray datasets to improve performance
Author: Charle Turner
Maintainer: Charles Turner
License: Apache Software License 2.0
Project-URL: bugs, https://github.com/charles-turner-1/xrexpr/issues
Project-URL: changelog, https://github.com/charles-turner-1/xrexpr/blob/main/CHANGELOG.md
Project-URL: homepage, https://github.com/charles-turner-1/xrexpr
Classifier: Development Status :: 4 - Beta
Classifier: Programming Language :: Python :: 3
Classifier: License :: OSI Approved :: Apache Software License
Classifier: Operating System :: OS Independent
Requires-Python: >=3.10
Requires-Dist: libcst
Requires-Dist: xarray
Provides-Extra: dev
Requires-Dist: coverage; extra == "dev"
Requires-Dist: mypy; extra == "dev"
Requires-Dist: pytest; extra == "dev"
Requires-Dist: ruff; extra == "dev"
Requires-Dist: xarray; extra == "dev"
